<?xml version="1.0" encoding="UTF-8"?>
<!DOCTYPE properties PUBLIC "-//java.sun.com//DTD PROPERTIES//EN" "http://java.sun.com/dtd/properties.dtd">
<properties>
	<entry key="resource_not_exists">{0}不存在</entry>
	<entry key="resource_no_permission">没有该{0}权限</entry>
	<entry key="invalid_sms_captcha">验证码无效</entry>
	<entry key="img_captcha_error">图形验证码错误</entry>
	<entry key="invalid_wx_appid">不可用的APPID: {0}</entry>
	<entry key="expire_wx_appid">授权已过期APPID: {0}</entry>
	<entry key="invalid_token">无效的Token</entry>

	<!-- 小程序错误信息模板 -->
	<entry key="-1">微信服务器系统繁忙，请稍候再试</entry>
	<entry key="40001">AppSecret错误或者AppSecret不属于这个公众号</entry>
	<entry key="40002">请确保grant_type字段值为client_credential</entry>
	<entry key="40037">template_id不正确</entry>
	<entry key="40164">用接口的IP地址不在白名单中，请在接口IP白名单中进行设置</entry>
	<entry key="41028">form_id不正确，或者过期</entry>
	<entry key="41029">form_id已被使用</entry>
	<entry key="41030">page不正确</entry>
	<entry key="45009">接口调用超过限额</entry>

	<entry key="file_analysis_param_error">文件解析参数有误</entry>
	<entry key="file_analysis_error">文件解析异常</entry>
	<entry key="file_not_excel">{0}不是excel文件</entry>
	<entry key="file_excel_not_exists">文件不存在</entry>
	<entry key="file_excel_sheet_num_error">Excel文件Sheet数有误</entry>
	<entry key="file_excel_sheet_colnum_error">Excel文件Sheet{0}中列数有误</entry>
	<entry key="file_excel_sheet_rownum_error">Excel文件Sheet{0}中行数超过最大{1}行</entry>
	
	<entry key="file_excel_biz_lockdog_need">Excel文件中必须存在加密狗数据</entry>
	<entry key="file_excel_biz_lockdog_eid_max">加密狗编号不能超过18位</entry>
	
	<!-- 业务错误信息模板 -->
	<entry key="public_captcha_error">图形验证码错误</entry>
	<entry key="public_mobivali_error">手机验证码错误</entry>
	<entry key="public_apiparam_blank">缺少必要接口参数。请检查：{0}</entry>
	
	<entry key="ali_sendmsg_error">短信发送失败：{0}</entry>
	<entry key="ali_sendmsg_overtimes">手机号:{0}发送次数过于频繁</entry>
	
	<entry key="info_not_exists">id：{0}对应信息不存在</entry>
    <entry key="info_edit_id_must">待修改的主KEY（id字段）必须</entry>
	
	<entry key="obdlic_bizdata_error">请求业务数据错误</entry>
	<entry key="obdlic_bizdata_error_expire">过期的请求数据</entry>
	<entry key="obdlic_rsa_error">请求加密数据错误</entry>
	<entry key="obdlic_rsa_id_nomatch">设备ID不匹配。ID：{0}</entry>
	<entry key="obdlic_active_already">该设备已存在使用中的授权。ID：{0}</entry>
	
	<entry key="obdcar_data_dirty">OBD存在脏数据</entry>
	<entry key="obdcar_not_devicenumber">deviceNumber不存在</entry>
	<entry key="obdcar_carinfo_nomatch">OBD的eid:{0}与deviceNumber：{1}不匹配</entry>
	<entry key="obdcar_eid_devicenumber_double">eid:{0}与deviceNumber：{1}匹配重复</entry>
	<entry key="obdcar_eid_devicenumber_already_exists">eid：{0}与deviceNumber：{1}已存在关联信息</entry>
	<entry key="obdcar_eid_already_exists">eid：{0}已存在deviceNumber关联信息</entry>
	<entry key="obdcar_devicenumber_already_exists">devicenumber：{0}已存在eid关联信息</entry>
	<entry key="obdcar_not_related">eid：{0}未关联OBD实时设备</entry>
	
	<entry key="carinfo_not_exists">eid：{0}车辆不存在</entry>
	<entry key="carinfo_already_exists">eid：{0}车辆已存在</entry>
	<entry key="carinfo_devicenumber_already_exists">devicenumber：{0}车辆已存在</entry>
	<entry key="carinfo_edit_id_must">待修改车辆的主KEY（id字段）必须</entry>
	<entry key="carinfo_not_exists">id：{0}车辆不存在</entry>

	<entry key="carinsur_already_exists">该车辆该保险已存在</entry>
	<entry key="carinsur_insurnum_already_exists">该保单号：{0}已存在</entry>
	
	<entry key="binduser_already_default">该分类人员已有默认设置</entry>
	
	<entry key="carmot_exists_expired">已存在晚于该车年检有效期的记录</entry>
	<entry key="carmot_nocar_exists">该年检对应的车辆不存在</entry>
	<entry key="carmot_expdate_over_max">该车年检有效期需小于{0}</entry>
	<entry key="carmot_expdate_over_min">该车年检有效期需大于{0}</entry>
</properties>